hat/monitor/server/ui/script/snabbdom/modules/attributes.js
hat/monitor/server/ui/script/snabbdom/vnode.js
hat/monitor/server/ui/script/@hat-open/util/json.d.ts
hat/monitor/server/ui/script/@hat-open/juggler/index.js
hat/monitor/server/ui/script/@hat-open/util/json.js
hat/monitor/server/ui/icons/LICENSE
hat/monitor/server/ui/script/snabbdom/modules/class.js.map
hat/monitor/server/ui/script/@hat-open/util/patch.d.ts
hat/monitor/json_schema_repo.json
hat/monitor/server/ui/script/snabbdom/hooks.d.ts
hat/monitor/server/ui/script/@hat-open/juggler/index.d.ts
hat/monitor/component.py
hat/monitor/server/ui/script/snabbdom/modules/dataset.js
hat/monitor/server/ui/script/snabbdom/init.js
hat/monitor/server/ui/script/snabbdom/vnode.js.map
hat/monitor/server/ui/script/snabbdom/hooks.js
hat/monitor/server/ui/script/@hat-open/util/package.json
hat/monitor/server/ui/script/snabbdom/is.js
hat/monitor/server/ui/script/@hat-open/util/iter.js
hat/monitor/server/ui/script/@hat-open/util/dragger.js
hat/monitor/server/ui/script/snabbdom/modules/dataset.d.ts
hat/monitor/server/ui/index.html
hat/monitor/server/ui/script/snabbdom/vnode.d.ts
hat/monitor/server/ui/script/snabbdom/modules/class.js
hat/monitor/server/ui/script/@hat-open/util/promise.js
hat/monitor/server/ui/script/snabbdom/helpers/attachto.js
hat/monitor/observer/master.py
hat/monitor/__init__.py
hat/monitor/server/runner.py
hat/monitor/server/ui/script/snabbdom/index.js.map
hat/monitor/server/ui/script/snabbdom/modules/eventlisteners.js
hat/monitor/server/ui/script/snabbdom/tovnode.js
hat/monitor/server/__main__.py
hat/monitor/server/ui/script/snabbdom/modules/module.js
hat/monitor/server/ui/script/snabbdom/modules/dataset.js.map
hat/monitor/server/ui/script/snabbdom/modules/attributes.js.map
hat/monitor/observer/client.py
hat/monitor/server/ui/script/@hat-open/util/promise.d.ts
hat/monitor/server/ui/script/@hat-open/util/pipe.d.ts
hat/monitor/server/ui/script/snabbdom/index.js
hat_monitor-0.8.19.dist-info/LICENSE
hat_monitor-0.8.19.dist-info/entry_points.txt
hat_monitor-0.8.19.dist-info/METADATA
hat_monitor-0.8.19.dist-info/WHEEL
hat_monitor-0.8.19.dist-info/RECORD
